usos_api/__init__.py
usos_api/auth.py
usos_api/client.py
usos_api/connection.py
usos_api/exceptions.py
usos_api/helper.py
usos_api/logger.py
usos_api/models/__init__.py
usos_api/models/api_documentation.py
usos_api/models/consumer.py
usos_api/models/course.py
usos_api/models/grade.py
usos_api/models/group.py
usos_api/models/lang_dict.py
usos_api/models/programme.py
usos_api/models/registration.py
usos_api/models/term.py
usos_api/models/user.py
usos_api/services/__init__.py
usos_api/services/api_documentation.py
usos_api/services/api_server.py
usos_api/services/courses.py
usos_api/services/grades.py
usos_api/services/groups.py
usos_api/services/registrations.py
usos_api/services/terms.py
usos_api/services/users.py
usos_api/utils/__init__.py
usos_api-0.3.2.dist-info/METADATA
usos_api-0.3.2.dist-info/WHEEL
usos_api-0.3.2.dist-info/RECORD
